simplehound/__init__.py
simplehound/core.py
simplehound-0.6.dist-info/LICENSE
simplehound-0.6.dist-info/METADATA
simplehound-0.6.dist-info/WHEEL
simplehound-0.6.dist-info/top_level.txt
simplehound-0.6.dist-info/RECORD
