Metadata-Version: 2.1
Name: simplehound
Version: 0.6
Summary: Unofficial python API for Sighthound
Home-page: https://github.com/robmarkcole/simplehound
Author: Robin Cole
Author-email: robmarkcole@gmail.com
License: Apache License, Version 2.0
Platform: UNKNOWN
Classifier: Intended Audience :: Developers
Classifier: Natural Language :: English
Classifier: Programming Language :: Python
Classifier: Programming Language :: Python :: 3
Requires-Python: >=3.6
Requires-Dist: requests
